{
  "generator-jhipster": {
    "applicationType": "monolith",
    "baseName": "picosoft5",
    "jhipsterVersion": "7.1.0",
    "skipClient": false,
    "skipServer": false,
    "skipUserManagement": false,
    "skipCheckLengthOfIdentifier": false,
    "skipFakeData": false,
    "jhiPrefix": "jhi",
    "entitySuffix": "",
    "dtoSuffix": "DTO",
    "testFrameworks": [],
    "blueprints": [],
    "otherModules": [],
    "pages": [],
    "creationTimestamp": 1628677774634,
    "serviceDiscoveryType": false,
    "reactive": false,
    "authenticationType": "jwt",
    "packageName": "com.picosoft.app",
    "serverPort": "8080",
    "cacheProvider": "ehcache",
    "enableHibernateCache": false,
    "databaseType": "sql",
    "devDatabaseType": "mysql",
    "prodDatabaseType": "mysql",
    "buildTool": "maven",
    "serverSideOptions": [],
    "websocket": false,
    "searchEngine": false,
    "messageBroker": false,
    "enableSwaggerCodegen": false,
    "clientFramework": "angularX",
    "withAdminUi": true,
    "clientTheme": "cyborg",
    "clientThemeVariant": "dark",
    "enableTranslation": false,
    "nativeLanguage": "fr",
    "packageFolder": "com/picosoft/app",
    "jwtSecretKey": "NjM1MmQwODYwMzg3ODI5MmI4NzQ3ZGVlYzUwMGU3YmRjNTNhMjU2OTE1MTFjZGFkYzJmZmQ5Y2U4YmIzZDE0ZTYzNTMxNjUzMWIzNTljODA3YmQyMzNlMGMyMGYzZWU5M2FkZDY2MWVkMGMxZmJmZjdlODEzZTgxNmExODI0NmE=",
    "devServerPort": 4200,
    "clientPackageManager": "npm",
    "languages": ["en", "fr"],
    "entities": ["Dossier", "Demande"],
    "lastLiquibaseTimestamp": 1628681909000
  }
}
